kaggle_downloader_package/__init__.py
kaggle_downloader_package/kaggle_downloader.py
kaggle_downloader_package-0.1.7.dist-info/LICENSE
kaggle_downloader_package-0.1.7.dist-info/METADATA
kaggle_downloader_package-0.1.7.dist-info/WHEEL
kaggle_downloader_package-0.1.7.dist-info/RECORD
