Metadata-Version: 2.1
Name: kaggle-downloader-package
Version: 0.1.7
Summary: A package to download datasets from Kaggle.
Home-page: https://github.com/Mgobeaalcoba/kaggle_downloader_package
License: MIT
Author: Mariano Daniel Gobea Alcoba
Author-email: gobeamariano@gmail.com
Requires-Python: >=3.9,<4.0
Classifier: License :: OSI Approved :: MIT License
Classifier: Programming Language :: Python :: 3
Classifier: Programming Language :: Python :: 3.9
Classifier: Programming Language :: Python :: 3.10
Classifier: Programming Language :: Python :: 3.11
Classifier: Programming Language :: Python :: 3.12
Requires-Dist: chardet (>=5.2.0,<6.0.0)
Requires-Dist: coverage (>=7.6.1,<8.0.0)
Requires-Dist: kaggle (>=1.6.17,<2.0.0)
Requires-Dist: nbformat (>=5.10.4,<6.0.0)
Requires-Dist: pandas (>=2.2.2,<3.0.0)
Requires-Dist: python-dotenv (>=1.0.1,<2.0.0)
Requires-Dist: requests (>=2.32.3,<3.0.0)
Requires-Dist: seaborn (>=0.13.2,<0.14.0)
Project-URL: Documentation, https://github.com/Mgobeaalcoba/kaggle_downloader_package
Project-URL: Repository, https://github.com/Mgobeaalcoba/kaggle_downloader_package
